{
    "ktkexq": {
        "ktkexq_benign_0": {
            "train": {
                "Benign": 38441,
                "Infilteration": 498
            },
            "test": {
                "Benign": 176304,
                "DDoS": 14697,
                "DoS": 5064,
                "Bot": 1440,
                "Brute Force": 1304,
                "Infilteration": 1185,
                "injection": 6
            }
        },
        "ktkexq_benign_1": {
            "train": {
                "Benign": 17220,
                "DoS": 2055
            },
            "test": {
                "Benign": 176304,
                "DDoS": 14697,
                "DoS": 5064,
                "Bot": 1440,
                "Brute Force": 1304,
                "Infilteration": 1185,
                "injection": 6
            }
        },
        "ktkexq_benign_2": {
            "train": {
                "Benign": 93176,
                "Brute Force": 520
            },
            "test": {
                "Benign": 176304,
                "DDoS": 14697,
                "DoS": 5064,
                "Bot": 1440,
                "Brute Force": 1304,
                "Infilteration": 1185,
                "injection": 6
            }
        },
        "ktkexq_benign_3": {
            "train": {
                "Benign": 60670,
                "Bot": 608
            },
            "test": {
                "Benign": 176304,
                "DDoS": 14697,
                "DoS": 5064,
                "Bot": 1440,
                "Brute Force": 1304,
                "Infilteration": 1185,
                "injection": 6
            }
        },
        "ktkexq_benign_4": {
            "train": {
                "Benign": 11094,
                "DDoS": 5887
            },
            "test": {
                "Benign": 176304,
                "DDoS": 14697,
                "DoS": 5064,
                "Bot": 1440,
                "Brute Force": 1304,
                "Infilteration": 1185,
                "injection": 6
            }
        },
        "ktkexq_malicious_0": {
            "train": {
                "Benign": 39306,
                "DoS": 2047
            },
            "test": {
                "Benign": 176304,
                "DDoS": 14697,
                "DoS": 5064,
                "Bot": 1440,
                "Brute Force": 1304,
                "Infilteration": 1185,
                "injection": 6
            }
        },
        "ktkexq_malicious_1": {
            "train": {
                "Benign": 144183,
                "Brute Force": 525
            },
            "test": {
                "Benign": 176304,
                "DDoS": 14697,
                "DoS": 5064,
                "Bot": 1440,
                "Brute Force": 1304,
                "Infilteration": 1185,
                "injection": 6
            }
        },
        "ktkexq_malicious_2": {
            "train": {
                "Benign": 52620,
                "DDoS": 5886
            },
            "test": {
                "Benign": 176304,
                "DDoS": 14697,
                "DoS": 5064,
                "Bot": 1440,
                "Brute Force": 1304,
                "Infilteration": 1185,
                "injection": 6
            }
        },
        "ktkexq_malicious_3": {
            "train": {
                "Benign": 149895,
                "Bot": 623
            },
            "test": {
                "Benign": 176304,
                "DDoS": 14697,
                "DoS": 5064,
                "Bot": 1440,
                "Brute Force": 1304,
                "Infilteration": 1185,
                "injection": 6
            }
        },
        "ktkexq_malicious_4": {
            "train": {
                "Benign": 97714,
                "DoS": 2047
            },
            "test": {
                "Benign": 176304,
                "DDoS": 14697,
                "DoS": 5064,
                "Bot": 1440,
                "Brute Force": 1304,
                "Infilteration": 1185,
                "injection": 6
            }
        }
    }
}