{
    "ktkexq_malicious_4": {
        "1": {
            "accuracy": 0.02569,
            "precision": 0.0174727165054567,
            "recall": 0.13042563044668043,
            "f1": 0.030816978185399236,
            "mcc": -0.875148301669727,
            "missrate": 0.8695743695533196,
            "fallout": 0.9884253348993174,
            "loss": 2.1074843406677246
        },
        "2": {
            "accuracy": 0.032685,
            "precision": 0.011389679039075007,
            "recall": 0.08327369174420073,
            "f1": 0.020038598108591373,
            "mcc": -0.8523409509157054,
            "missrate": 0.9167263082557993,
            "fallout": 0.9741328930421511,
            "loss": 2.3894355297088623
        },
        "3": {
            "accuracy": 0.966875,
            "precision": 0.8973276422009836,
            "recall": 0.8142550414684461,
            "f1": 0.8537753548016863,
            "mcc": 0.8363999271240575,
            "missrate": 0.1857449585315539,
            "fallout": 0.012556242092063978,
            "loss": 0.11041297018527985
        },
        "4": {
            "accuracy": 0.9849,
            "precision": 0.9600177501664078,
            "recall": 0.9107902159727193,
            "f1": 0.9347563083304529,
            "mcc": 0.9266352478528043,
            "missrate": 0.08920978402728076,
            "fallout": 0.0051121437528014665,
            "loss": 0.07032278180122375
        },
        "5": {
            "accuracy": 0.9865,
            "precision": 0.9685316241598789,
            "recall": 0.9160948090767482,
            "f1": 0.9415837299870187,
            "mcc": 0.9344209369332643,
            "missrate": 0.0839051909232518,
            "fallout": 0.00401141579714832,
            "loss": 0.05661320686340332
        },
        "6": {
            "accuracy": 0.98873,
            "precision": 0.9746125656761888,
            "recall": 0.9293141918915505,
            "f1": 0.9514245075643291,
            "mcc": 0.9453965419658654,
            "missrate": 0.07068580810844946,
            "fallout": 0.0032624668788688604,
            "loss": 0.05033606290817261
        },
        "7": {
            "accuracy": 0.990055,
            "precision": 0.9773644499034918,
            "recall": 0.9379867806171852,
            "f1": 0.9572708328857762,
            "mcc": 0.9519038080412704,
            "missrate": 0.0620132193828148,
            "fallout": 0.0029277094078197074,
            "loss": 0.04707058146595955
        },
        "8": {
            "accuracy": 0.990155,
            "precision": 0.9778031233549745,
            "recall": 0.9384077800698859,
            "f1": 0.9577004876581666,
            "mcc": 0.9523901523185698,
            "missrate": 0.061592219930114094,
            "fallout": 0.002870970853404597,
            "loss": 0.04496646299958229
        },
        "9": {
            "accuracy": 0.990245,
            "precision": 0.9784917917654289,
            "recall": 0.9384919799604261,
            "f1": 0.9580745675298163,
            "mcc": 0.9528232892622502,
            "missrate": 0.06150802003957395,
            "fallout": 0.00278018916634042,
            "loss": 0.04335024952888489
        },
        "10": {
            "accuracy": 0.990385,
            "precision": 0.9792325254654022,
            "recall": 0.9389550793583968,
            "f1": 0.9586709364052526,
            "mcc": 0.9535025061992684,
            "missrate": 0.06104492064160317,
            "fallout": 0.002683733623834732,
            "loss": 0.04201670363545418,
            "attack_stats": [
                {
                    "attack": "DDoS",
                    "count": 14650,
                    "correct": 14185,
                    "missed": 465,
                    "percentage": "96.83%"
                },
                {
                    "attack": "DoS",
                    "count": 5076,
                    "correct": 5045,
                    "missed": 31,
                    "percentage": "99.39%"
                },
                {
                    "attack": "Bot",
                    "count": 1482,
                    "correct": 1482,
                    "missed": 0,
                    "percentage": "100.00%"
                },
                {
                    "attack": "Brute Force",
                    "count": 1333,
                    "correct": 1325,
                    "missed": 8,
                    "percentage": "99.40%"
                },
                {
                    "attack": "Infilteration",
                    "count": 1209,
                    "correct": 264,
                    "missed": 945,
                    "percentage": "21.84%"
                },
                {
                    "attack": "injection",
                    "count": 3,
                    "correct": 2,
                    "missed": 1,
                    "percentage": "66.67%"
                }
            ]
        }
    },
    "ktkexq_malicious_3": {
        "1": {
            "accuracy": 0.02569,
            "precision": 0.0174727165054567,
            "recall": 0.13042563044668043,
            "f1": 0.030816978185399236,
            "mcc": -0.875148301669727,
            "missrate": 0.8695743695533196,
            "fallout": 0.9884253348993174,
            "loss": 2.1074843406677246
        },
        "2": {
            "accuracy": 0.032685,
            "precision": 0.011389679039075007,
            "recall": 0.08327369174420073,
            "f1": 0.020038598108591373,
            "mcc": -0.8523409509157054,
            "missrate": 0.9167263082557993,
            "fallout": 0.9741328930421511,
            "loss": 2.3894355297088623
        },
        "3": {
            "accuracy": 0.966875,
            "precision": 0.8973276422009836,
            "recall": 0.8142550414684461,
            "f1": 0.8537753548016863,
            "mcc": 0.8363999271240575,
            "missrate": 0.1857449585315539,
            "fallout": 0.012556242092063978,
            "loss": 0.11041297018527985
        },
        "4": {
            "accuracy": 0.9849,
            "precision": 0.9600177501664078,
            "recall": 0.9107902159727193,
            "f1": 0.9347563083304529,
            "mcc": 0.9266352478528043,
            "missrate": 0.08920978402728076,
            "fallout": 0.0051121437528014665,
            "loss": 0.07032278180122375
        },
        "5": {
            "accuracy": 0.9865,
            "precision": 0.9685316241598789,
            "recall": 0.9160948090767482,
            "f1": 0.9415837299870187,
            "mcc": 0.9344209369332643,
            "missrate": 0.0839051909232518,
            "fallout": 0.00401141579714832,
            "loss": 0.05661320686340332
        },
        "6": {
            "accuracy": 0.98873,
            "precision": 0.9746125656761888,
            "recall": 0.9293141918915505,
            "f1": 0.9514245075643291,
            "mcc": 0.9453965419658654,
            "missrate": 0.07068580810844946,
            "fallout": 0.0032624668788688604,
            "loss": 0.05033606290817261
        },
        "7": {
            "accuracy": 0.990055,
            "precision": 0.9773644499034918,
            "recall": 0.9379867806171852,
            "f1": 0.9572708328857762,
            "mcc": 0.9519038080412704,
            "missrate": 0.0620132193828148,
            "fallout": 0.0029277094078197074,
            "loss": 0.04707058146595955
        },
        "8": {
            "accuracy": 0.990155,
            "precision": 0.9778031233549745,
            "recall": 0.9384077800698859,
            "f1": 0.9577004876581666,
            "mcc": 0.9523901523185698,
            "missrate": 0.061592219930114094,
            "fallout": 0.002870970853404597,
            "loss": 0.04496646299958229
        },
        "9": {
            "accuracy": 0.990245,
            "precision": 0.9784917917654289,
            "recall": 0.9384919799604261,
            "f1": 0.9580745675298163,
            "mcc": 0.9528232892622502,
            "missrate": 0.06150802003957395,
            "fallout": 0.00278018916634042,
            "loss": 0.04335024952888489
        },
        "10": {
            "accuracy": 0.990385,
            "precision": 0.9792325254654022,
            "recall": 0.9389550793583968,
            "f1": 0.9586709364052526,
            "mcc": 0.9535025061992684,
            "missrate": 0.06104492064160317,
            "fallout": 0.002683733623834732,
            "loss": 0.04201670363545418,
            "attack_stats": [
                {
                    "attack": "DDoS",
                    "count": 14650,
                    "correct": 14185,
                    "missed": 465,
                    "percentage": "96.83%"
                },
                {
                    "attack": "DoS",
                    "count": 5076,
                    "correct": 5045,
                    "missed": 31,
                    "percentage": "99.39%"
                },
                {
                    "attack": "Bot",
                    "count": 1482,
                    "correct": 1482,
                    "missed": 0,
                    "percentage": "100.00%"
                },
                {
                    "attack": "Brute Force",
                    "count": 1333,
                    "correct": 1325,
                    "missed": 8,
                    "percentage": "99.40%"
                },
                {
                    "attack": "Infilteration",
                    "count": 1209,
                    "correct": 264,
                    "missed": 945,
                    "percentage": "21.84%"
                },
                {
                    "attack": "injection",
                    "count": 3,
                    "correct": 2,
                    "missed": 1,
                    "percentage": "66.67%"
                }
            ]
        }
    },
    "ktkexq_benign_1": {
        "1": {
            "accuracy": 0.02569,
            "precision": 0.0174727165054567,
            "recall": 0.13042563044668043,
            "f1": 0.030816978185399236,
            "mcc": -0.875148301669727,
            "missrate": 0.8695743695533196,
            "fallout": 0.9884253348993174,
            "loss": 2.1074843406677246
        },
        "2": {
            "accuracy": 0.032685,
            "precision": 0.011389679039075007,
            "recall": 0.08327369174420073,
            "f1": 0.020038598108591373,
            "mcc": -0.8523409509157054,
            "missrate": 0.9167263082557993,
            "fallout": 0.9741328930421511,
            "loss": 2.3894355297088623
        },
        "3": {
            "accuracy": 0.966875,
            "precision": 0.8973276422009836,
            "recall": 0.8142550414684461,
            "f1": 0.8537753548016863,
            "mcc": 0.8363999271240575,
            "missrate": 0.1857449585315539,
            "fallout": 0.012556242092063978,
            "loss": 0.11041297018527985
        },
        "4": {
            "accuracy": 0.9849,
            "precision": 0.9600177501664078,
            "recall": 0.9107902159727193,
            "f1": 0.9347563083304529,
            "mcc": 0.9266352478528043,
            "missrate": 0.08920978402728076,
            "fallout": 0.0051121437528014665,
            "loss": 0.07032278180122375
        },
        "5": {
            "accuracy": 0.9865,
            "precision": 0.9685316241598789,
            "recall": 0.9160948090767482,
            "f1": 0.9415837299870187,
            "mcc": 0.9344209369332643,
            "missrate": 0.0839051909232518,
            "fallout": 0.00401141579714832,
            "loss": 0.05661320686340332
        },
        "6": {
            "accuracy": 0.98873,
            "precision": 0.9746125656761888,
            "recall": 0.9293141918915505,
            "f1": 0.9514245075643291,
            "mcc": 0.9453965419658654,
            "missrate": 0.07068580810844946,
            "fallout": 0.0032624668788688604,
            "loss": 0.05033606290817261
        },
        "7": {
            "accuracy": 0.990055,
            "precision": 0.9773644499034918,
            "recall": 0.9379867806171852,
            "f1": 0.9572708328857762,
            "mcc": 0.9519038080412704,
            "missrate": 0.0620132193828148,
            "fallout": 0.0029277094078197074,
            "loss": 0.04707058146595955
        },
        "8": {
            "accuracy": 0.990155,
            "precision": 0.9778031233549745,
            "recall": 0.9384077800698859,
            "f1": 0.9577004876581666,
            "mcc": 0.9523901523185698,
            "missrate": 0.061592219930114094,
            "fallout": 0.002870970853404597,
            "loss": 0.04496646299958229
        },
        "9": {
            "accuracy": 0.990245,
            "precision": 0.9784917917654289,
            "recall": 0.9384919799604261,
            "f1": 0.9580745675298163,
            "mcc": 0.9528232892622502,
            "missrate": 0.06150802003957395,
            "fallout": 0.00278018916634042,
            "loss": 0.04335024952888489
        },
        "10": {
            "accuracy": 0.990385,
            "precision": 0.9792325254654022,
            "recall": 0.9389550793583968,
            "f1": 0.9586709364052526,
            "mcc": 0.9535025061992684,
            "missrate": 0.06104492064160317,
            "fallout": 0.002683733623834732,
            "loss": 0.04201670363545418,
            "attack_stats": [
                {
                    "attack": "DDoS",
                    "count": 14650,
                    "correct": 14185,
                    "missed": 465,
                    "percentage": "96.83%"
                },
                {
                    "attack": "DoS",
                    "count": 5076,
                    "correct": 5045,
                    "missed": 31,
                    "percentage": "99.39%"
                },
                {
                    "attack": "Bot",
                    "count": 1482,
                    "correct": 1482,
                    "missed": 0,
                    "percentage": "100.00%"
                },
                {
                    "attack": "Brute Force",
                    "count": 1333,
                    "correct": 1325,
                    "missed": 8,
                    "percentage": "99.40%"
                },
                {
                    "attack": "Infilteration",
                    "count": 1209,
                    "correct": 264,
                    "missed": 945,
                    "percentage": "21.84%"
                },
                {
                    "attack": "injection",
                    "count": 3,
                    "correct": 2,
                    "missed": 1,
                    "percentage": "66.67%"
                }
            ]
        }
    },
    "ktkexq_benign_2": {
        "1": {
            "accuracy": 0.02569,
            "precision": 0.0174727165054567,
            "recall": 0.13042563044668043,
            "f1": 0.030816978185399236,
            "mcc": -0.875148301669727,
            "missrate": 0.8695743695533196,
            "fallout": 0.9884253348993174,
            "loss": 2.1074843406677246
        },
        "2": {
            "accuracy": 0.032685,
            "precision": 0.011389679039075007,
            "recall": 0.08327369174420073,
            "f1": 0.020038598108591373,
            "mcc": -0.8523409509157054,
            "missrate": 0.9167263082557993,
            "fallout": 0.9741328930421511,
            "loss": 2.3894355297088623
        },
        "3": {
            "accuracy": 0.966875,
            "precision": 0.8973276422009836,
            "recall": 0.8142550414684461,
            "f1": 0.8537753548016863,
            "mcc": 0.8363999271240575,
            "missrate": 0.1857449585315539,
            "fallout": 0.012556242092063978,
            "loss": 0.11041297018527985
        },
        "4": {
            "accuracy": 0.9849,
            "precision": 0.9600177501664078,
            "recall": 0.9107902159727193,
            "f1": 0.9347563083304529,
            "mcc": 0.9266352478528043,
            "missrate": 0.08920978402728076,
            "fallout": 0.0051121437528014665,
            "loss": 0.07032278180122375
        },
        "5": {
            "accuracy": 0.9865,
            "precision": 0.9685316241598789,
            "recall": 0.9160948090767482,
            "f1": 0.9415837299870187,
            "mcc": 0.9344209369332643,
            "missrate": 0.0839051909232518,
            "fallout": 0.00401141579714832,
            "loss": 0.05661320686340332
        },
        "6": {
            "accuracy": 0.98873,
            "precision": 0.9746125656761888,
            "recall": 0.9293141918915505,
            "f1": 0.9514245075643291,
            "mcc": 0.9453965419658654,
            "missrate": 0.07068580810844946,
            "fallout": 0.0032624668788688604,
            "loss": 0.05033606290817261
        },
        "7": {
            "accuracy": 0.990055,
            "precision": 0.9773644499034918,
            "recall": 0.9379867806171852,
            "f1": 0.9572708328857762,
            "mcc": 0.9519038080412704,
            "missrate": 0.0620132193828148,
            "fallout": 0.0029277094078197074,
            "loss": 0.04707058146595955
        },
        "8": {
            "accuracy": 0.990155,
            "precision": 0.9778031233549745,
            "recall": 0.9384077800698859,
            "f1": 0.9577004876581666,
            "mcc": 0.9523901523185698,
            "missrate": 0.061592219930114094,
            "fallout": 0.002870970853404597,
            "loss": 0.04496646299958229
        },
        "9": {
            "accuracy": 0.990245,
            "precision": 0.9784917917654289,
            "recall": 0.9384919799604261,
            "f1": 0.9580745675298163,
            "mcc": 0.9528232892622502,
            "missrate": 0.06150802003957395,
            "fallout": 0.00278018916634042,
            "loss": 0.04335024952888489
        },
        "10": {
            "accuracy": 0.990385,
            "precision": 0.9792325254654022,
            "recall": 0.9389550793583968,
            "f1": 0.9586709364052526,
            "mcc": 0.9535025061992684,
            "missrate": 0.06104492064160317,
            "fallout": 0.002683733623834732,
            "loss": 0.04201670363545418,
            "attack_stats": [
                {
                    "attack": "DDoS",
                    "count": 14650,
                    "correct": 14185,
                    "missed": 465,
                    "percentage": "96.83%"
                },
                {
                    "attack": "DoS",
                    "count": 5076,
                    "correct": 5045,
                    "missed": 31,
                    "percentage": "99.39%"
                },
                {
                    "attack": "Bot",
                    "count": 1482,
                    "correct": 1482,
                    "missed": 0,
                    "percentage": "100.00%"
                },
                {
                    "attack": "Brute Force",
                    "count": 1333,
                    "correct": 1325,
                    "missed": 8,
                    "percentage": "99.40%"
                },
                {
                    "attack": "Infilteration",
                    "count": 1209,
                    "correct": 264,
                    "missed": 945,
                    "percentage": "21.84%"
                },
                {
                    "attack": "injection",
                    "count": 3,
                    "correct": 2,
                    "missed": 1,
                    "percentage": "66.67%"
                }
            ]
        }
    },
    "ktkexq_malicious_0": {
        "1": {
            "accuracy": 0.02569,
            "precision": 0.0174727165054567,
            "recall": 0.13042563044668043,
            "f1": 0.030816978185399236,
            "mcc": -0.875148301669727,
            "missrate": 0.8695743695533196,
            "fallout": 0.9884253348993174,
            "loss": 2.1074843406677246
        },
        "2": {
            "accuracy": 0.032685,
            "precision": 0.011389679039075007,
            "recall": 0.08327369174420073,
            "f1": 0.020038598108591373,
            "mcc": -0.8523409509157054,
            "missrate": 0.9167263082557993,
            "fallout": 0.9741328930421511,
            "loss": 2.3894355297088623
        },
        "3": {
            "accuracy": 0.966875,
            "precision": 0.8973276422009836,
            "recall": 0.8142550414684461,
            "f1": 0.8537753548016863,
            "mcc": 0.8363999271240575,
            "missrate": 0.1857449585315539,
            "fallout": 0.012556242092063978,
            "loss": 0.11041297018527985
        },
        "4": {
            "accuracy": 0.9849,
            "precision": 0.9600177501664078,
            "recall": 0.9107902159727193,
            "f1": 0.9347563083304529,
            "mcc": 0.9266352478528043,
            "missrate": 0.08920978402728076,
            "fallout": 0.0051121437528014665,
            "loss": 0.07032278180122375
        },
        "5": {
            "accuracy": 0.9865,
            "precision": 0.9685316241598789,
            "recall": 0.9160948090767482,
            "f1": 0.9415837299870187,
            "mcc": 0.9344209369332643,
            "missrate": 0.0839051909232518,
            "fallout": 0.00401141579714832,
            "loss": 0.05661320686340332
        },
        "6": {
            "accuracy": 0.98873,
            "precision": 0.9746125656761888,
            "recall": 0.9293141918915505,
            "f1": 0.9514245075643291,
            "mcc": 0.9453965419658654,
            "missrate": 0.07068580810844946,
            "fallout": 0.0032624668788688604,
            "loss": 0.05033606290817261
        },
        "7": {
            "accuracy": 0.990055,
            "precision": 0.9773644499034918,
            "recall": 0.9379867806171852,
            "f1": 0.9572708328857762,
            "mcc": 0.9519038080412704,
            "missrate": 0.0620132193828148,
            "fallout": 0.0029277094078197074,
            "loss": 0.04707058146595955
        },
        "8": {
            "accuracy": 0.990155,
            "precision": 0.9778031233549745,
            "recall": 0.9384077800698859,
            "f1": 0.9577004876581666,
            "mcc": 0.9523901523185698,
            "missrate": 0.061592219930114094,
            "fallout": 0.002870970853404597,
            "loss": 0.04496646299958229
        },
        "9": {
            "accuracy": 0.990245,
            "precision": 0.9784917917654289,
            "recall": 0.9384919799604261,
            "f1": 0.9580745675298163,
            "mcc": 0.9528232892622502,
            "missrate": 0.06150802003957395,
            "fallout": 0.00278018916634042,
            "loss": 0.04335024952888489
        },
        "10": {
            "accuracy": 0.990385,
            "precision": 0.9792325254654022,
            "recall": 0.9389550793583968,
            "f1": 0.9586709364052526,
            "mcc": 0.9535025061992684,
            "missrate": 0.06104492064160317,
            "fallout": 0.002683733623834732,
            "loss": 0.04201670363545418,
            "attack_stats": [
                {
                    "attack": "DDoS",
                    "count": 14650,
                    "correct": 14185,
                    "missed": 465,
                    "percentage": "96.83%"
                },
                {
                    "attack": "DoS",
                    "count": 5076,
                    "correct": 5045,
                    "missed": 31,
                    "percentage": "99.39%"
                },
                {
                    "attack": "Bot",
                    "count": 1482,
                    "correct": 1482,
                    "missed": 0,
                    "percentage": "100.00%"
                },
                {
                    "attack": "Brute Force",
                    "count": 1333,
                    "correct": 1325,
                    "missed": 8,
                    "percentage": "99.40%"
                },
                {
                    "attack": "Infilteration",
                    "count": 1209,
                    "correct": 264,
                    "missed": 945,
                    "percentage": "21.84%"
                },
                {
                    "attack": "injection",
                    "count": 3,
                    "correct": 2,
                    "missed": 1,
                    "percentage": "66.67%"
                }
            ]
        }
    },
    "ktkexq_malicious_5": {
        "1": {
            "accuracy": 0.02569,
            "precision": 0.0174727165054567,
            "recall": 0.13042563044668043,
            "f1": 0.030816978185399236,
            "mcc": -0.875148301669727,
            "missrate": 0.8695743695533196,
            "fallout": 0.9884253348993174,
            "loss": 2.1074843406677246
        },
        "2": {
            "accuracy": 0.032685,
            "precision": 0.011389679039075007,
            "recall": 0.08327369174420073,
            "f1": 0.020038598108591373,
            "mcc": -0.8523409509157054,
            "missrate": 0.9167263082557993,
            "fallout": 0.9741328930421511,
            "loss": 2.3894355297088623
        },
        "3": {
            "accuracy": 0.966875,
            "precision": 0.8973276422009836,
            "recall": 0.8142550414684461,
            "f1": 0.8537753548016863,
            "mcc": 0.8363999271240575,
            "missrate": 0.1857449585315539,
            "fallout": 0.012556242092063978,
            "loss": 0.11041297018527985
        },
        "4": {
            "accuracy": 0.9849,
            "precision": 0.9600177501664078,
            "recall": 0.9107902159727193,
            "f1": 0.9347563083304529,
            "mcc": 0.9266352478528043,
            "missrate": 0.08920978402728076,
            "fallout": 0.0051121437528014665,
            "loss": 0.07032278180122375
        },
        "5": {
            "accuracy": 0.9865,
            "precision": 0.9685316241598789,
            "recall": 0.9160948090767482,
            "f1": 0.9415837299870187,
            "mcc": 0.9344209369332643,
            "missrate": 0.0839051909232518,
            "fallout": 0.00401141579714832,
            "loss": 0.05661320686340332
        },
        "6": {
            "accuracy": 0.98873,
            "precision": 0.9746125656761888,
            "recall": 0.9293141918915505,
            "f1": 0.9514245075643291,
            "mcc": 0.9453965419658654,
            "missrate": 0.07068580810844946,
            "fallout": 0.0032624668788688604,
            "loss": 0.05033606290817261
        },
        "7": {
            "accuracy": 0.990055,
            "precision": 0.9773644499034918,
            "recall": 0.9379867806171852,
            "f1": 0.9572708328857762,
            "mcc": 0.9519038080412704,
            "missrate": 0.0620132193828148,
            "fallout": 0.0029277094078197074,
            "loss": 0.04707058146595955
        },
        "8": {
            "accuracy": 0.990155,
            "precision": 0.9778031233549745,
            "recall": 0.9384077800698859,
            "f1": 0.9577004876581666,
            "mcc": 0.9523901523185698,
            "missrate": 0.061592219930114094,
            "fallout": 0.002870970853404597,
            "loss": 0.04496646299958229
        },
        "9": {
            "accuracy": 0.990245,
            "precision": 0.9784917917654289,
            "recall": 0.9384919799604261,
            "f1": 0.9580745675298163,
            "mcc": 0.9528232892622502,
            "missrate": 0.06150802003957395,
            "fallout": 0.00278018916634042,
            "loss": 0.04335024952888489
        },
        "10": {
            "accuracy": 0.990385,
            "precision": 0.9792325254654022,
            "recall": 0.9389550793583968,
            "f1": 0.9586709364052526,
            "mcc": 0.9535025061992684,
            "missrate": 0.06104492064160317,
            "fallout": 0.002683733623834732,
            "loss": 0.04201670363545418,
            "attack_stats": [
                {
                    "attack": "DDoS",
                    "count": 14650,
                    "correct": 14185,
                    "missed": 465,
                    "percentage": "96.83%"
                },
                {
                    "attack": "DoS",
                    "count": 5076,
                    "correct": 5045,
                    "missed": 31,
                    "percentage": "99.39%"
                },
                {
                    "attack": "Bot",
                    "count": 1482,
                    "correct": 1482,
                    "missed": 0,
                    "percentage": "100.00%"
                },
                {
                    "attack": "Brute Force",
                    "count": 1333,
                    "correct": 1325,
                    "missed": 8,
                    "percentage": "99.40%"
                },
                {
                    "attack": "Infilteration",
                    "count": 1209,
                    "correct": 264,
                    "missed": 945,
                    "percentage": "21.84%"
                },
                {
                    "attack": "injection",
                    "count": 3,
                    "correct": 2,
                    "missed": 1,
                    "percentage": "66.67%"
                }
            ]
        }
    },
    "ktkexq_benign_0": {
        "1": {
            "accuracy": 0.02569,
            "precision": 0.0174727165054567,
            "recall": 0.13042563044668043,
            "f1": 0.030816978185399236,
            "mcc": -0.875148301669727,
            "missrate": 0.8695743695533196,
            "fallout": 0.9884253348993174,
            "loss": 2.1074843406677246
        },
        "2": {
            "accuracy": 0.032685,
            "precision": 0.011389679039075007,
            "recall": 0.08327369174420073,
            "f1": 0.020038598108591373,
            "mcc": -0.8523409509157054,
            "missrate": 0.9167263082557993,
            "fallout": 0.9741328930421511,
            "loss": 2.3894355297088623
        },
        "3": {
            "accuracy": 0.966875,
            "precision": 0.8973276422009836,
            "recall": 0.8142550414684461,
            "f1": 0.8537753548016863,
            "mcc": 0.8363999271240575,
            "missrate": 0.1857449585315539,
            "fallout": 0.012556242092063978,
            "loss": 0.11041297018527985
        },
        "4": {
            "accuracy": 0.9849,
            "precision": 0.9600177501664078,
            "recall": 0.9107902159727193,
            "f1": 0.9347563083304529,
            "mcc": 0.9266352478528043,
            "missrate": 0.08920978402728076,
            "fallout": 0.0051121437528014665,
            "loss": 0.07032278180122375
        },
        "5": {
            "accuracy": 0.9865,
            "precision": 0.9685316241598789,
            "recall": 0.9160948090767482,
            "f1": 0.9415837299870187,
            "mcc": 0.9344209369332643,
            "missrate": 0.0839051909232518,
            "fallout": 0.00401141579714832,
            "loss": 0.05661320686340332
        },
        "6": {
            "accuracy": 0.98873,
            "precision": 0.9746125656761888,
            "recall": 0.9293141918915505,
            "f1": 0.9514245075643291,
            "mcc": 0.9453965419658654,
            "missrate": 0.07068580810844946,
            "fallout": 0.0032624668788688604,
            "loss": 0.05033606290817261
        },
        "7": {
            "accuracy": 0.990055,
            "precision": 0.9773644499034918,
            "recall": 0.9379867806171852,
            "f1": 0.9572708328857762,
            "mcc": 0.9519038080412704,
            "missrate": 0.0620132193828148,
            "fallout": 0.0029277094078197074,
            "loss": 0.04707058146595955
        },
        "8": {
            "accuracy": 0.990155,
            "precision": 0.9778031233549745,
            "recall": 0.9384077800698859,
            "f1": 0.9577004876581666,
            "mcc": 0.9523901523185698,
            "missrate": 0.061592219930114094,
            "fallout": 0.002870970853404597,
            "loss": 0.04496646299958229
        },
        "9": {
            "accuracy": 0.990245,
            "precision": 0.9784917917654289,
            "recall": 0.9384919799604261,
            "f1": 0.9580745675298163,
            "mcc": 0.9528232892622502,
            "missrate": 0.06150802003957395,
            "fallout": 0.00278018916634042,
            "loss": 0.04335024952888489
        },
        "10": {
            "accuracy": 0.990385,
            "precision": 0.9792325254654022,
            "recall": 0.9389550793583968,
            "f1": 0.9586709364052526,
            "mcc": 0.9535025061992684,
            "missrate": 0.06104492064160317,
            "fallout": 0.002683733623834732,
            "loss": 0.04201670363545418,
            "attack_stats": [
                {
                    "attack": "DDoS",
                    "count": 14650,
                    "correct": 14185,
                    "missed": 465,
                    "percentage": "96.83%"
                },
                {
                    "attack": "DoS",
                    "count": 5076,
                    "correct": 5045,
                    "missed": 31,
                    "percentage": "99.39%"
                },
                {
                    "attack": "Bot",
                    "count": 1482,
                    "correct": 1482,
                    "missed": 0,
                    "percentage": "100.00%"
                },
                {
                    "attack": "Brute Force",
                    "count": 1333,
                    "correct": 1325,
                    "missed": 8,
                    "percentage": "99.40%"
                },
                {
                    "attack": "Infilteration",
                    "count": 1209,
                    "correct": 264,
                    "missed": 945,
                    "percentage": "21.84%"
                },
                {
                    "attack": "injection",
                    "count": 3,
                    "correct": 2,
                    "missed": 1,
                    "percentage": "66.67%"
                }
            ]
        }
    },
    "ktkexq_malicious_6": {
        "1": {
            "accuracy": 0.02569,
            "precision": 0.0174727165054567,
            "recall": 0.13042563044668043,
            "f1": 0.030816978185399236,
            "mcc": -0.875148301669727,
            "missrate": 0.8695743695533196,
            "fallout": 0.9884253348993174,
            "loss": 2.1074843406677246
        },
        "2": {
            "accuracy": 0.032685,
            "precision": 0.011389679039075007,
            "recall": 0.08327369174420073,
            "f1": 0.020038598108591373,
            "mcc": -0.8523409509157054,
            "missrate": 0.9167263082557993,
            "fallout": 0.9741328930421511,
            "loss": 2.3894355297088623
        },
        "3": {
            "accuracy": 0.966875,
            "precision": 0.8973276422009836,
            "recall": 0.8142550414684461,
            "f1": 0.8537753548016863,
            "mcc": 0.8363999271240575,
            "missrate": 0.1857449585315539,
            "fallout": 0.012556242092063978,
            "loss": 0.11041297018527985
        },
        "4": {
            "accuracy": 0.9849,
            "precision": 0.9600177501664078,
            "recall": 0.9107902159727193,
            "f1": 0.9347563083304529,
            "mcc": 0.9266352478528043,
            "missrate": 0.08920978402728076,
            "fallout": 0.0051121437528014665,
            "loss": 0.07032278180122375
        },
        "5": {
            "accuracy": 0.9865,
            "precision": 0.9685316241598789,
            "recall": 0.9160948090767482,
            "f1": 0.9415837299870187,
            "mcc": 0.9344209369332643,
            "missrate": 0.0839051909232518,
            "fallout": 0.00401141579714832,
            "loss": 0.05661320686340332
        },
        "6": {
            "accuracy": 0.98873,
            "precision": 0.9746125656761888,
            "recall": 0.9293141918915505,
            "f1": 0.9514245075643291,
            "mcc": 0.9453965419658654,
            "missrate": 0.07068580810844946,
            "fallout": 0.0032624668788688604,
            "loss": 0.05033606290817261
        },
        "7": {
            "accuracy": 0.990055,
            "precision": 0.9773644499034918,
            "recall": 0.9379867806171852,
            "f1": 0.9572708328857762,
            "mcc": 0.9519038080412704,
            "missrate": 0.0620132193828148,
            "fallout": 0.0029277094078197074,
            "loss": 0.04707058146595955
        },
        "8": {
            "accuracy": 0.990155,
            "precision": 0.9778031233549745,
            "recall": 0.9384077800698859,
            "f1": 0.9577004876581666,
            "mcc": 0.9523901523185698,
            "missrate": 0.061592219930114094,
            "fallout": 0.002870970853404597,
            "loss": 0.04496646299958229
        },
        "9": {
            "accuracy": 0.990245,
            "precision": 0.9784917917654289,
            "recall": 0.9384919799604261,
            "f1": 0.9580745675298163,
            "mcc": 0.9528232892622502,
            "missrate": 0.06150802003957395,
            "fallout": 0.00278018916634042,
            "loss": 0.04335024952888489
        },
        "10": {
            "accuracy": 0.990385,
            "precision": 0.9792325254654022,
            "recall": 0.9389550793583968,
            "f1": 0.9586709364052526,
            "mcc": 0.9535025061992684,
            "missrate": 0.06104492064160317,
            "fallout": 0.002683733623834732,
            "loss": 0.04201670363545418,
            "attack_stats": [
                {
                    "attack": "DDoS",
                    "count": 14650,
                    "correct": 14185,
                    "missed": 465,
                    "percentage": "96.83%"
                },
                {
                    "attack": "DoS",
                    "count": 5076,
                    "correct": 5045,
                    "missed": 31,
                    "percentage": "99.39%"
                },
                {
                    "attack": "Bot",
                    "count": 1482,
                    "correct": 1482,
                    "missed": 0,
                    "percentage": "100.00%"
                },
                {
                    "attack": "Brute Force",
                    "count": 1333,
                    "correct": 1325,
                    "missed": 8,
                    "percentage": "99.40%"
                },
                {
                    "attack": "Infilteration",
                    "count": 1209,
                    "correct": 264,
                    "missed": 945,
                    "percentage": "21.84%"
                },
                {
                    "attack": "injection",
                    "count": 3,
                    "correct": 2,
                    "missed": 1,
                    "percentage": "66.67%"
                }
            ]
        }
    },
    "ktkexq_malicious_1": {
        "1": {
            "accuracy": 0.02569,
            "precision": 0.0174727165054567,
            "recall": 0.13042563044668043,
            "f1": 0.030816978185399236,
            "mcc": -0.875148301669727,
            "missrate": 0.8695743695533196,
            "fallout": 0.9884253348993174,
            "loss": 2.1074843406677246
        },
        "2": {
            "accuracy": 0.032685,
            "precision": 0.011389679039075007,
            "recall": 0.08327369174420073,
            "f1": 0.020038598108591373,
            "mcc": -0.8523409509157054,
            "missrate": 0.9167263082557993,
            "fallout": 0.9741328930421511,
            "loss": 2.3894355297088623
        },
        "3": {
            "accuracy": 0.966875,
            "precision": 0.8973276422009836,
            "recall": 0.8142550414684461,
            "f1": 0.8537753548016863,
            "mcc": 0.8363999271240575,
            "missrate": 0.1857449585315539,
            "fallout": 0.012556242092063978,
            "loss": 0.11041297018527985
        },
        "4": {
            "accuracy": 0.9849,
            "precision": 0.9600177501664078,
            "recall": 0.9107902159727193,
            "f1": 0.9347563083304529,
            "mcc": 0.9266352478528043,
            "missrate": 0.08920978402728076,
            "fallout": 0.0051121437528014665,
            "loss": 0.07032278180122375
        },
        "5": {
            "accuracy": 0.9865,
            "precision": 0.9685316241598789,
            "recall": 0.9160948090767482,
            "f1": 0.9415837299870187,
            "mcc": 0.9344209369332643,
            "missrate": 0.0839051909232518,
            "fallout": 0.00401141579714832,
            "loss": 0.05661320686340332
        },
        "6": {
            "accuracy": 0.98873,
            "precision": 0.9746125656761888,
            "recall": 0.9293141918915505,
            "f1": 0.9514245075643291,
            "mcc": 0.9453965419658654,
            "missrate": 0.07068580810844946,
            "fallout": 0.0032624668788688604,
            "loss": 0.05033606290817261
        },
        "7": {
            "accuracy": 0.990055,
            "precision": 0.9773644499034918,
            "recall": 0.9379867806171852,
            "f1": 0.9572708328857762,
            "mcc": 0.9519038080412704,
            "missrate": 0.0620132193828148,
            "fallout": 0.0029277094078197074,
            "loss": 0.04707058146595955
        },
        "8": {
            "accuracy": 0.990155,
            "precision": 0.9778031233549745,
            "recall": 0.9384077800698859,
            "f1": 0.9577004876581666,
            "mcc": 0.9523901523185698,
            "missrate": 0.061592219930114094,
            "fallout": 0.002870970853404597,
            "loss": 0.04496646299958229
        },
        "9": {
            "accuracy": 0.990245,
            "precision": 0.9784917917654289,
            "recall": 0.9384919799604261,
            "f1": 0.9580745675298163,
            "mcc": 0.9528232892622502,
            "missrate": 0.06150802003957395,
            "fallout": 0.00278018916634042,
            "loss": 0.04335024952888489
        },
        "10": {
            "accuracy": 0.990385,
            "precision": 0.9792325254654022,
            "recall": 0.9389550793583968,
            "f1": 0.9586709364052526,
            "mcc": 0.9535025061992684,
            "missrate": 0.06104492064160317,
            "fallout": 0.002683733623834732,
            "loss": 0.04201670363545418,
            "attack_stats": [
                {
                    "attack": "DDoS",
                    "count": 14650,
                    "correct": 14185,
                    "missed": 465,
                    "percentage": "96.83%"
                },
                {
                    "attack": "DoS",
                    "count": 5076,
                    "correct": 5045,
                    "missed": 31,
                    "percentage": "99.39%"
                },
                {
                    "attack": "Bot",
                    "count": 1482,
                    "correct": 1482,
                    "missed": 0,
                    "percentage": "100.00%"
                },
                {
                    "attack": "Brute Force",
                    "count": 1333,
                    "correct": 1325,
                    "missed": 8,
                    "percentage": "99.40%"
                },
                {
                    "attack": "Infilteration",
                    "count": 1209,
                    "correct": 264,
                    "missed": 945,
                    "percentage": "21.84%"
                },
                {
                    "attack": "injection",
                    "count": 3,
                    "correct": 2,
                    "missed": 1,
                    "percentage": "66.67%"
                }
            ]
        }
    },
    "ktkexq_malicious_2": {
        "1": {
            "accuracy": 0.02569,
            "precision": 0.0174727165054567,
            "recall": 0.13042563044668043,
            "f1": 0.030816978185399236,
            "mcc": -0.875148301669727,
            "missrate": 0.8695743695533196,
            "fallout": 0.9884253348993174,
            "loss": 2.1074843406677246
        },
        "2": {
            "accuracy": 0.032685,
            "precision": 0.011389679039075007,
            "recall": 0.08327369174420073,
            "f1": 0.020038598108591373,
            "mcc": -0.8523409509157054,
            "missrate": 0.9167263082557993,
            "fallout": 0.9741328930421511,
            "loss": 2.3894355297088623
        },
        "3": {
            "accuracy": 0.966875,
            "precision": 0.8973276422009836,
            "recall": 0.8142550414684461,
            "f1": 0.8537753548016863,
            "mcc": 0.8363999271240575,
            "missrate": 0.1857449585315539,
            "fallout": 0.012556242092063978,
            "loss": 0.11041297018527985
        },
        "4": {
            "accuracy": 0.9849,
            "precision": 0.9600177501664078,
            "recall": 0.9107902159727193,
            "f1": 0.9347563083304529,
            "mcc": 0.9266352478528043,
            "missrate": 0.08920978402728076,
            "fallout": 0.0051121437528014665,
            "loss": 0.07032278180122375
        },
        "5": {
            "accuracy": 0.9865,
            "precision": 0.9685316241598789,
            "recall": 0.9160948090767482,
            "f1": 0.9415837299870187,
            "mcc": 0.9344209369332643,
            "missrate": 0.0839051909232518,
            "fallout": 0.00401141579714832,
            "loss": 0.05661320686340332
        },
        "6": {
            "accuracy": 0.98873,
            "precision": 0.9746125656761888,
            "recall": 0.9293141918915505,
            "f1": 0.9514245075643291,
            "mcc": 0.9453965419658654,
            "missrate": 0.07068580810844946,
            "fallout": 0.0032624668788688604,
            "loss": 0.05033606290817261
        },
        "7": {
            "accuracy": 0.990055,
            "precision": 0.9773644499034918,
            "recall": 0.9379867806171852,
            "f1": 0.9572708328857762,
            "mcc": 0.9519038080412704,
            "missrate": 0.0620132193828148,
            "fallout": 0.0029277094078197074,
            "loss": 0.04707058146595955
        },
        "8": {
            "accuracy": 0.990155,
            "precision": 0.9778031233549745,
            "recall": 0.9384077800698859,
            "f1": 0.9577004876581666,
            "mcc": 0.9523901523185698,
            "missrate": 0.061592219930114094,
            "fallout": 0.002870970853404597,
            "loss": 0.04496646299958229
        },
        "9": {
            "accuracy": 0.990245,
            "precision": 0.9784917917654289,
            "recall": 0.9384919799604261,
            "f1": 0.9580745675298163,
            "mcc": 0.9528232892622502,
            "missrate": 0.06150802003957395,
            "fallout": 0.00278018916634042,
            "loss": 0.04335024952888489
        },
        "10": {
            "accuracy": 0.990385,
            "precision": 0.9792325254654022,
            "recall": 0.9389550793583968,
            "f1": 0.9586709364052526,
            "mcc": 0.9535025061992684,
            "missrate": 0.06104492064160317,
            "fallout": 0.002683733623834732,
            "loss": 0.04201670363545418,
            "attack_stats": [
                {
                    "attack": "DDoS",
                    "count": 14650,
                    "correct": 14185,
                    "missed": 465,
                    "percentage": "96.83%"
                },
                {
                    "attack": "DoS",
                    "count": 5076,
                    "correct": 5045,
                    "missed": 31,
                    "percentage": "99.39%"
                },
                {
                    "attack": "Bot",
                    "count": 1482,
                    "correct": 1482,
                    "missed": 0,
                    "percentage": "100.00%"
                },
                {
                    "attack": "Brute Force",
                    "count": 1333,
                    "correct": 1325,
                    "missed": 8,
                    "percentage": "99.40%"
                },
                {
                    "attack": "Infilteration",
                    "count": 1209,
                    "correct": 264,
                    "missed": 945,
                    "percentage": "21.84%"
                },
                {
                    "attack": "injection",
                    "count": 3,
                    "correct": 2,
                    "missed": 1,
                    "percentage": "66.67%"
                }
            ]
        }
    }
}