{
    "ktkexq_benign_7": {
        "1": {
            "accuracy": 0.986355,
            "precision": 0.9724528975801411,
            "recall": 0.9116059096806596,
            "f1": 0.941046855760299,
            "mcc": 0.9339635087872042,
            "missrate": 0.0883940903193404,
            "fallout": 0.0035035518179288728,
            "loss": 0.06227315589785576
        },
        "2": {
            "accuracy": 0.988195,
            "precision": 0.9737722232001408,
            "recall": 0.9261289917549073,
            "f1": 0.9493532402342493,
            "mcc": 0.9430567792663678,
            "missrate": 0.07387100824509271,
            "fallout": 0.003384306132067436,
            "loss": 0.04991440102458
        },
        "3": {
            "accuracy": 0.98943,
            "precision": 0.9737654992386339,
            "recall": 0.9367597204202067,
            "f1": 0.9549042194632876,
            "mcc": 0.9491486276981853,
            "missrate": 0.06324027957979325,
            "fallout": 0.0034240546940212486,
            "loss": 0.057494085282087326
        },
        "4": {
            "accuracy": 0.991475,
            "precision": 0.9871344515675771,
            "recall": 0.9409031934039258,
            "f1": 0.9634645466818095,
            "mcc": 0.9589955509769089,
            "missrate": 0.059096806596074164,
            "fallout": 0.0016637612360667095,
            "loss": 0.05693511292338371
        },
        "5": {
            "accuracy": 0.99179,
            "precision": 0.9896140474409189,
            "recall": 0.9411543129786967,
            "f1": 0.9647760425604942,
            "mcc": 0.9605204842825892,
            "missrate": 0.058845687021303314,
            "fallout": 0.0013400943744428103,
            "loss": 0.05406133458018303
        },
        "6": {
            "accuracy": 0.993755,
            "precision": 0.9905971054684115,
            "recall": 0.9568074331394132,
            "f1": 0.9734091247791191,
            "mcc": 0.9700598480801107,
            "missrate": 0.043192566860586784,
            "fallout": 0.0012322054205681774,
            "loss": 0.050382766872644424
        },
        "7": {
            "accuracy": 0.99415,
            "precision": 0.9937850406362727,
            "recall": 0.9570166994517223,
            "f1": 0.9750543686836383,
            "mcc": 0.9719637285132376,
            "missrate": 0.04298330054827774,
            "fallout": 0.0008120063370564486,
            "loss": 0.048006586730480194
        },
        "8": {
            "accuracy": 0.994195,
            "precision": 0.9940879846983134,
            "recall": 0.9571004059766459,
            "f1": 0.9752436189948185,
            "mcc": 0.9721811240267432,
            "missrate": 0.04289959402335412,
            "fallout": 0.0007722577751026364,
            "loss": 0.04396862909197807
        },
        "9": {
            "accuracy": 0.994285,
            "precision": 0.9948233861144945,
            "recall": 0.9571422592391077,
            "f1": 0.9756191207525438,
            "mcc": 0.972616160037576,
            "missrate": 0.04285774076089231,
            "fallout": 0.0006757255532148069,
            "loss": 0.04240183159708977
        },
        "10": {
            "accuracy": 0.994285,
            "precision": 0.9946942680699313,
            "recall": 0.9572678190264932,
            "f1": 0.9756222407063793,
            "mcc": 0.9726160824126554,
            "missrate": 0.04273218097350689,
            "fallout": 0.0006927606511950121,
            "loss": 0.038429144769907,
            "attack_stats": [
                {
                    "attack": "Brute Force",
                    "count": 1306,
                    "correct": 1302,
                    "missed": 4,
                    "percentage": "99.69%"
                },
                {
                    "attack": "DDoS",
                    "count": 14745,
                    "correct": 14722,
                    "missed": 23,
                    "percentage": "99.84%"
                },
                {
                    "attack": "DoS",
                    "count": 5106,
                    "correct": 5078,
                    "missed": 28,
                    "percentage": "99.45%"
                },
                {
                    "attack": "Infilteration",
                    "count": 1231,
                    "correct": 266,
                    "missed": 965,
                    "percentage": "21.61%"
                },
                {
                    "attack": "Bot",
                    "count": 1503,
                    "correct": 1502,
                    "missed": 1,
                    "percentage": "99.93%"
                },
                {
                    "attack": "injection",
                    "count": 2,
                    "correct": 2,
                    "missed": 0,
                    "percentage": "100.00%"
                }
            ]
        }
    },
    "ktkexq_benign_4": {
        "1": {
            "accuracy": 0.986355,
            "precision": 0.9724528975801411,
            "recall": 0.9116059096806596,
            "f1": 0.941046855760299,
            "mcc": 0.9339635087872042,
            "missrate": 0.0883940903193404,
            "fallout": 0.0035035518179288728,
            "loss": 0.06227315589785576
        },
        "2": {
            "accuracy": 0.988195,
            "precision": 0.9737722232001408,
            "recall": 0.9261289917549073,
            "f1": 0.9493532402342493,
            "mcc": 0.9430567792663678,
            "missrate": 0.07387100824509271,
            "fallout": 0.003384306132067436,
            "loss": 0.04991440102458
        },
        "3": {
            "accuracy": 0.98943,
            "precision": 0.9737654992386339,
            "recall": 0.9367597204202067,
            "f1": 0.9549042194632876,
            "mcc": 0.9491486276981853,
            "missrate": 0.06324027957979325,
            "fallout": 0.0034240546940212486,
            "loss": 0.057494085282087326
        },
        "4": {
            "accuracy": 0.991475,
            "precision": 0.9871344515675771,
            "recall": 0.9409031934039258,
            "f1": 0.9634645466818095,
            "mcc": 0.9589955509769089,
            "missrate": 0.059096806596074164,
            "fallout": 0.0016637612360667095,
            "loss": 0.05693511292338371
        },
        "5": {
            "accuracy": 0.99179,
            "precision": 0.9896140474409189,
            "recall": 0.9411543129786967,
            "f1": 0.9647760425604942,
            "mcc": 0.9605204842825892,
            "missrate": 0.058845687021303314,
            "fallout": 0.0013400943744428103,
            "loss": 0.05406133458018303
        },
        "6": {
            "accuracy": 0.993755,
            "precision": 0.9905971054684115,
            "recall": 0.9568074331394132,
            "f1": 0.9734091247791191,
            "mcc": 0.9700598480801107,
            "missrate": 0.043192566860586784,
            "fallout": 0.0012322054205681774,
            "loss": 0.050382766872644424
        },
        "7": {
            "accuracy": 0.99415,
            "precision": 0.9937850406362727,
            "recall": 0.9570166994517223,
            "f1": 0.9750543686836383,
            "mcc": 0.9719637285132376,
            "missrate": 0.04298330054827774,
            "fallout": 0.0008120063370564486,
            "loss": 0.048006586730480194
        },
        "8": {
            "accuracy": 0.994195,
            "precision": 0.9940879846983134,
            "recall": 0.9571004059766459,
            "f1": 0.9752436189948185,
            "mcc": 0.9721811240267432,
            "missrate": 0.04289959402335412,
            "fallout": 0.0007722577751026364,
            "loss": 0.04396862909197807
        },
        "9": {
            "accuracy": 0.994285,
            "precision": 0.9948233861144945,
            "recall": 0.9571422592391077,
            "f1": 0.9756191207525438,
            "mcc": 0.972616160037576,
            "missrate": 0.04285774076089231,
            "fallout": 0.0006757255532148069,
            "loss": 0.04240183159708977
        },
        "10": {
            "accuracy": 0.994285,
            "precision": 0.9946942680699313,
            "recall": 0.9572678190264932,
            "f1": 0.9756222407063793,
            "mcc": 0.9726160824126554,
            "missrate": 0.04273218097350689,
            "fallout": 0.0006927606511950121,
            "loss": 0.038429144769907,
            "attack_stats": [
                {
                    "attack": "Brute Force",
                    "count": 1306,
                    "correct": 1302,
                    "missed": 4,
                    "percentage": "99.69%"
                },
                {
                    "attack": "DDoS",
                    "count": 14745,
                    "correct": 14722,
                    "missed": 23,
                    "percentage": "99.84%"
                },
                {
                    "attack": "DoS",
                    "count": 5106,
                    "correct": 5078,
                    "missed": 28,
                    "percentage": "99.45%"
                },
                {
                    "attack": "Infilteration",
                    "count": 1231,
                    "correct": 266,
                    "missed": 965,
                    "percentage": "21.61%"
                },
                {
                    "attack": "Bot",
                    "count": 1503,
                    "correct": 1502,
                    "missed": 1,
                    "percentage": "99.93%"
                },
                {
                    "attack": "injection",
                    "count": 2,
                    "correct": 2,
                    "missed": 0,
                    "percentage": "100.00%"
                }
            ]
        }
    },
    "ktkexq_benign_5": {
        "1": {
            "accuracy": 0.986355,
            "precision": 0.9724528975801411,
            "recall": 0.9116059096806596,
            "f1": 0.941046855760299,
            "mcc": 0.9339635087872042,
            "missrate": 0.0883940903193404,
            "fallout": 0.0035035518179288728,
            "loss": 0.06227315589785576
        },
        "2": {
            "accuracy": 0.988195,
            "precision": 0.9737722232001408,
            "recall": 0.9261289917549073,
            "f1": 0.9493532402342493,
            "mcc": 0.9430567792663678,
            "missrate": 0.07387100824509271,
            "fallout": 0.003384306132067436,
            "loss": 0.04991440102458
        },
        "3": {
            "accuracy": 0.98943,
            "precision": 0.9737654992386339,
            "recall": 0.9367597204202067,
            "f1": 0.9549042194632876,
            "mcc": 0.9491486276981853,
            "missrate": 0.06324027957979325,
            "fallout": 0.0034240546940212486,
            "loss": 0.057494085282087326
        },
        "4": {
            "accuracy": 0.991475,
            "precision": 0.9871344515675771,
            "recall": 0.9409031934039258,
            "f1": 0.9634645466818095,
            "mcc": 0.9589955509769089,
            "missrate": 0.059096806596074164,
            "fallout": 0.0016637612360667095,
            "loss": 0.05693511292338371
        },
        "5": {
            "accuracy": 0.99179,
            "precision": 0.9896140474409189,
            "recall": 0.9411543129786967,
            "f1": 0.9647760425604942,
            "mcc": 0.9605204842825892,
            "missrate": 0.058845687021303314,
            "fallout": 0.0013400943744428103,
            "loss": 0.05406133458018303
        },
        "6": {
            "accuracy": 0.993755,
            "precision": 0.9905971054684115,
            "recall": 0.9568074331394132,
            "f1": 0.9734091247791191,
            "mcc": 0.9700598480801107,
            "missrate": 0.043192566860586784,
            "fallout": 0.0012322054205681774,
            "loss": 0.050382766872644424
        },
        "7": {
            "accuracy": 0.99415,
            "precision": 0.9937850406362727,
            "recall": 0.9570166994517223,
            "f1": 0.9750543686836383,
            "mcc": 0.9719637285132376,
            "missrate": 0.04298330054827774,
            "fallout": 0.0008120063370564486,
            "loss": 0.048006586730480194
        },
        "8": {
            "accuracy": 0.994195,
            "precision": 0.9940879846983134,
            "recall": 0.9571004059766459,
            "f1": 0.9752436189948185,
            "mcc": 0.9721811240267432,
            "missrate": 0.04289959402335412,
            "fallout": 0.0007722577751026364,
            "loss": 0.04396862909197807
        },
        "9": {
            "accuracy": 0.994285,
            "precision": 0.9948233861144945,
            "recall": 0.9571422592391077,
            "f1": 0.9756191207525438,
            "mcc": 0.972616160037576,
            "missrate": 0.04285774076089231,
            "fallout": 0.0006757255532148069,
            "loss": 0.04240183159708977
        },
        "10": {
            "accuracy": 0.994285,
            "precision": 0.9946942680699313,
            "recall": 0.9572678190264932,
            "f1": 0.9756222407063793,
            "mcc": 0.9726160824126554,
            "missrate": 0.04273218097350689,
            "fallout": 0.0006927606511950121,
            "loss": 0.038429144769907,
            "attack_stats": [
                {
                    "attack": "Brute Force",
                    "count": 1306,
                    "correct": 1302,
                    "missed": 4,
                    "percentage": "99.69%"
                },
                {
                    "attack": "DDoS",
                    "count": 14745,
                    "correct": 14722,
                    "missed": 23,
                    "percentage": "99.84%"
                },
                {
                    "attack": "DoS",
                    "count": 5106,
                    "correct": 5078,
                    "missed": 28,
                    "percentage": "99.45%"
                },
                {
                    "attack": "Infilteration",
                    "count": 1231,
                    "correct": 266,
                    "missed": 965,
                    "percentage": "21.61%"
                },
                {
                    "attack": "Bot",
                    "count": 1503,
                    "correct": 1502,
                    "missed": 1,
                    "percentage": "99.93%"
                },
                {
                    "attack": "injection",
                    "count": 2,
                    "correct": 2,
                    "missed": 0,
                    "percentage": "100.00%"
                }
            ]
        }
    },
    "ktkexq_benign_3": {
        "1": {
            "accuracy": 0.986355,
            "precision": 0.9724528975801411,
            "recall": 0.9116059096806596,
            "f1": 0.941046855760299,
            "mcc": 0.9339635087872042,
            "missrate": 0.0883940903193404,
            "fallout": 0.0035035518179288728,
            "loss": 0.06227315589785576
        },
        "2": {
            "accuracy": 0.988195,
            "precision": 0.9737722232001408,
            "recall": 0.9261289917549073,
            "f1": 0.9493532402342493,
            "mcc": 0.9430567792663678,
            "missrate": 0.07387100824509271,
            "fallout": 0.003384306132067436,
            "loss": 0.04991440102458
        },
        "3": {
            "accuracy": 0.98943,
            "precision": 0.9737654992386339,
            "recall": 0.9367597204202067,
            "f1": 0.9549042194632876,
            "mcc": 0.9491486276981853,
            "missrate": 0.06324027957979325,
            "fallout": 0.0034240546940212486,
            "loss": 0.057494085282087326
        },
        "4": {
            "accuracy": 0.991475,
            "precision": 0.9871344515675771,
            "recall": 0.9409031934039258,
            "f1": 0.9634645466818095,
            "mcc": 0.9589955509769089,
            "missrate": 0.059096806596074164,
            "fallout": 0.0016637612360667095,
            "loss": 0.05693511292338371
        },
        "5": {
            "accuracy": 0.99179,
            "precision": 0.9896140474409189,
            "recall": 0.9411543129786967,
            "f1": 0.9647760425604942,
            "mcc": 0.9605204842825892,
            "missrate": 0.058845687021303314,
            "fallout": 0.0013400943744428103,
            "loss": 0.05406133458018303
        },
        "6": {
            "accuracy": 0.993755,
            "precision": 0.9905971054684115,
            "recall": 0.9568074331394132,
            "f1": 0.9734091247791191,
            "mcc": 0.9700598480801107,
            "missrate": 0.043192566860586784,
            "fallout": 0.0012322054205681774,
            "loss": 0.050382766872644424
        },
        "7": {
            "accuracy": 0.99415,
            "precision": 0.9937850406362727,
            "recall": 0.9570166994517223,
            "f1": 0.9750543686836383,
            "mcc": 0.9719637285132376,
            "missrate": 0.04298330054827774,
            "fallout": 0.0008120063370564486,
            "loss": 0.048006586730480194
        },
        "8": {
            "accuracy": 0.994195,
            "precision": 0.9940879846983134,
            "recall": 0.9571004059766459,
            "f1": 0.9752436189948185,
            "mcc": 0.9721811240267432,
            "missrate": 0.04289959402335412,
            "fallout": 0.0007722577751026364,
            "loss": 0.04396862909197807
        },
        "9": {
            "accuracy": 0.994285,
            "precision": 0.9948233861144945,
            "recall": 0.9571422592391077,
            "f1": 0.9756191207525438,
            "mcc": 0.972616160037576,
            "missrate": 0.04285774076089231,
            "fallout": 0.0006757255532148069,
            "loss": 0.04240183159708977
        },
        "10": {
            "accuracy": 0.994285,
            "precision": 0.9946942680699313,
            "recall": 0.9572678190264932,
            "f1": 0.9756222407063793,
            "mcc": 0.9726160824126554,
            "missrate": 0.04273218097350689,
            "fallout": 0.0006927606511950121,
            "loss": 0.038429144769907,
            "attack_stats": [
                {
                    "attack": "Brute Force",
                    "count": 1306,
                    "correct": 1302,
                    "missed": 4,
                    "percentage": "99.69%"
                },
                {
                    "attack": "DDoS",
                    "count": 14745,
                    "correct": 14722,
                    "missed": 23,
                    "percentage": "99.84%"
                },
                {
                    "attack": "DoS",
                    "count": 5106,
                    "correct": 5078,
                    "missed": 28,
                    "percentage": "99.45%"
                },
                {
                    "attack": "Infilteration",
                    "count": 1231,
                    "correct": 266,
                    "missed": 965,
                    "percentage": "21.61%"
                },
                {
                    "attack": "Bot",
                    "count": 1503,
                    "correct": 1502,
                    "missed": 1,
                    "percentage": "99.93%"
                },
                {
                    "attack": "injection",
                    "count": 2,
                    "correct": 2,
                    "missed": 0,
                    "percentage": "100.00%"
                }
            ]
        }
    },
    "ktkexq_benign_8": {
        "1": {
            "accuracy": 0.986355,
            "precision": 0.9724528975801411,
            "recall": 0.9116059096806596,
            "f1": 0.941046855760299,
            "mcc": 0.9339635087872042,
            "missrate": 0.0883940903193404,
            "fallout": 0.0035035518179288728,
            "loss": 0.06227315589785576
        },
        "2": {
            "accuracy": 0.988195,
            "precision": 0.9737722232001408,
            "recall": 0.9261289917549073,
            "f1": 0.9493532402342493,
            "mcc": 0.9430567792663678,
            "missrate": 0.07387100824509271,
            "fallout": 0.003384306132067436,
            "loss": 0.04991440102458
        },
        "3": {
            "accuracy": 0.98943,
            "precision": 0.9737654992386339,
            "recall": 0.9367597204202067,
            "f1": 0.9549042194632876,
            "mcc": 0.9491486276981853,
            "missrate": 0.06324027957979325,
            "fallout": 0.0034240546940212486,
            "loss": 0.057494085282087326
        },
        "4": {
            "accuracy": 0.991475,
            "precision": 0.9871344515675771,
            "recall": 0.9409031934039258,
            "f1": 0.9634645466818095,
            "mcc": 0.9589955509769089,
            "missrate": 0.059096806596074164,
            "fallout": 0.0016637612360667095,
            "loss": 0.05693511292338371
        },
        "5": {
            "accuracy": 0.99179,
            "precision": 0.9896140474409189,
            "recall": 0.9411543129786967,
            "f1": 0.9647760425604942,
            "mcc": 0.9605204842825892,
            "missrate": 0.058845687021303314,
            "fallout": 0.0013400943744428103,
            "loss": 0.05406133458018303
        },
        "6": {
            "accuracy": 0.993755,
            "precision": 0.9905971054684115,
            "recall": 0.9568074331394132,
            "f1": 0.9734091247791191,
            "mcc": 0.9700598480801107,
            "missrate": 0.043192566860586784,
            "fallout": 0.0012322054205681774,
            "loss": 0.050382766872644424
        },
        "7": {
            "accuracy": 0.99415,
            "precision": 0.9937850406362727,
            "recall": 0.9570166994517223,
            "f1": 0.9750543686836383,
            "mcc": 0.9719637285132376,
            "missrate": 0.04298330054827774,
            "fallout": 0.0008120063370564486,
            "loss": 0.048006586730480194
        },
        "8": {
            "accuracy": 0.994195,
            "precision": 0.9940879846983134,
            "recall": 0.9571004059766459,
            "f1": 0.9752436189948185,
            "mcc": 0.9721811240267432,
            "missrate": 0.04289959402335412,
            "fallout": 0.0007722577751026364,
            "loss": 0.04396862909197807
        },
        "9": {
            "accuracy": 0.994285,
            "precision": 0.9948233861144945,
            "recall": 0.9571422592391077,
            "f1": 0.9756191207525438,
            "mcc": 0.972616160037576,
            "missrate": 0.04285774076089231,
            "fallout": 0.0006757255532148069,
            "loss": 0.04240183159708977
        },
        "10": {
            "accuracy": 0.994285,
            "precision": 0.9946942680699313,
            "recall": 0.9572678190264932,
            "f1": 0.9756222407063793,
            "mcc": 0.9726160824126554,
            "missrate": 0.04273218097350689,
            "fallout": 0.0006927606511950121,
            "loss": 0.038429144769907,
            "attack_stats": [
                {
                    "attack": "Brute Force",
                    "count": 1306,
                    "correct": 1302,
                    "missed": 4,
                    "percentage": "99.69%"
                },
                {
                    "attack": "DDoS",
                    "count": 14745,
                    "correct": 14722,
                    "missed": 23,
                    "percentage": "99.84%"
                },
                {
                    "attack": "DoS",
                    "count": 5106,
                    "correct": 5078,
                    "missed": 28,
                    "percentage": "99.45%"
                },
                {
                    "attack": "Infilteration",
                    "count": 1231,
                    "correct": 266,
                    "missed": 965,
                    "percentage": "21.61%"
                },
                {
                    "attack": "Bot",
                    "count": 1503,
                    "correct": 1502,
                    "missed": 1,
                    "percentage": "99.93%"
                },
                {
                    "attack": "injection",
                    "count": 2,
                    "correct": 2,
                    "missed": 0,
                    "percentage": "100.00%"
                }
            ]
        }
    },
    "ktkexq_benign_0": {
        "1": {
            "accuracy": 0.986355,
            "precision": 0.9724528975801411,
            "recall": 0.9116059096806596,
            "f1": 0.941046855760299,
            "mcc": 0.9339635087872042,
            "missrate": 0.0883940903193404,
            "fallout": 0.0035035518179288728,
            "loss": 0.06227315589785576
        },
        "2": {
            "accuracy": 0.988195,
            "precision": 0.9737722232001408,
            "recall": 0.9261289917549073,
            "f1": 0.9493532402342493,
            "mcc": 0.9430567792663678,
            "missrate": 0.07387100824509271,
            "fallout": 0.003384306132067436,
            "loss": 0.04991440102458
        },
        "3": {
            "accuracy": 0.98943,
            "precision": 0.9737654992386339,
            "recall": 0.9367597204202067,
            "f1": 0.9549042194632876,
            "mcc": 0.9491486276981853,
            "missrate": 0.06324027957979325,
            "fallout": 0.0034240546940212486,
            "loss": 0.057494085282087326
        },
        "4": {
            "accuracy": 0.991475,
            "precision": 0.9871344515675771,
            "recall": 0.9409031934039258,
            "f1": 0.9634645466818095,
            "mcc": 0.9589955509769089,
            "missrate": 0.059096806596074164,
            "fallout": 0.0016637612360667095,
            "loss": 0.05693511292338371
        },
        "5": {
            "accuracy": 0.99179,
            "precision": 0.9896140474409189,
            "recall": 0.9411543129786967,
            "f1": 0.9647760425604942,
            "mcc": 0.9605204842825892,
            "missrate": 0.058845687021303314,
            "fallout": 0.0013400943744428103,
            "loss": 0.05406133458018303
        },
        "6": {
            "accuracy": 0.993755,
            "precision": 0.9905971054684115,
            "recall": 0.9568074331394132,
            "f1": 0.9734091247791191,
            "mcc": 0.9700598480801107,
            "missrate": 0.043192566860586784,
            "fallout": 0.0012322054205681774,
            "loss": 0.050382766872644424
        },
        "7": {
            "accuracy": 0.99415,
            "precision": 0.9937850406362727,
            "recall": 0.9570166994517223,
            "f1": 0.9750543686836383,
            "mcc": 0.9719637285132376,
            "missrate": 0.04298330054827774,
            "fallout": 0.0008120063370564486,
            "loss": 0.048006586730480194
        },
        "8": {
            "accuracy": 0.994195,
            "precision": 0.9940879846983134,
            "recall": 0.9571004059766459,
            "f1": 0.9752436189948185,
            "mcc": 0.9721811240267432,
            "missrate": 0.04289959402335412,
            "fallout": 0.0007722577751026364,
            "loss": 0.04396862909197807
        },
        "9": {
            "accuracy": 0.994285,
            "precision": 0.9948233861144945,
            "recall": 0.9571422592391077,
            "f1": 0.9756191207525438,
            "mcc": 0.972616160037576,
            "missrate": 0.04285774076089231,
            "fallout": 0.0006757255532148069,
            "loss": 0.04240183159708977
        },
        "10": {
            "accuracy": 0.994285,
            "precision": 0.9946942680699313,
            "recall": 0.9572678190264932,
            "f1": 0.9756222407063793,
            "mcc": 0.9726160824126554,
            "missrate": 0.04273218097350689,
            "fallout": 0.0006927606511950121,
            "loss": 0.038429144769907,
            "attack_stats": [
                {
                    "attack": "Brute Force",
                    "count": 1306,
                    "correct": 1302,
                    "missed": 4,
                    "percentage": "99.69%"
                },
                {
                    "attack": "DDoS",
                    "count": 14745,
                    "correct": 14722,
                    "missed": 23,
                    "percentage": "99.84%"
                },
                {
                    "attack": "DoS",
                    "count": 5106,
                    "correct": 5078,
                    "missed": 28,
                    "percentage": "99.45%"
                },
                {
                    "attack": "Infilteration",
                    "count": 1231,
                    "correct": 266,
                    "missed": 965,
                    "percentage": "21.61%"
                },
                {
                    "attack": "Bot",
                    "count": 1503,
                    "correct": 1502,
                    "missed": 1,
                    "percentage": "99.93%"
                },
                {
                    "attack": "injection",
                    "count": 2,
                    "correct": 2,
                    "missed": 0,
                    "percentage": "100.00%"
                }
            ]
        }
    },
    "ktkexq_benign_1": {
        "1": {
            "accuracy": 0.986355,
            "precision": 0.9724528975801411,
            "recall": 0.9116059096806596,
            "f1": 0.941046855760299,
            "mcc": 0.9339635087872042,
            "missrate": 0.0883940903193404,
            "fallout": 0.0035035518179288728,
            "loss": 0.06227315589785576
        },
        "2": {
            "accuracy": 0.988195,
            "precision": 0.9737722232001408,
            "recall": 0.9261289917549073,
            "f1": 0.9493532402342493,
            "mcc": 0.9430567792663678,
            "missrate": 0.07387100824509271,
            "fallout": 0.003384306132067436,
            "loss": 0.04991440102458
        },
        "3": {
            "accuracy": 0.98943,
            "precision": 0.9737654992386339,
            "recall": 0.9367597204202067,
            "f1": 0.9549042194632876,
            "mcc": 0.9491486276981853,
            "missrate": 0.06324027957979325,
            "fallout": 0.0034240546940212486,
            "loss": 0.057494085282087326
        },
        "4": {
            "accuracy": 0.991475,
            "precision": 0.9871344515675771,
            "recall": 0.9409031934039258,
            "f1": 0.9634645466818095,
            "mcc": 0.9589955509769089,
            "missrate": 0.059096806596074164,
            "fallout": 0.0016637612360667095,
            "loss": 0.05693511292338371
        },
        "5": {
            "accuracy": 0.99179,
            "precision": 0.9896140474409189,
            "recall": 0.9411543129786967,
            "f1": 0.9647760425604942,
            "mcc": 0.9605204842825892,
            "missrate": 0.058845687021303314,
            "fallout": 0.0013400943744428103,
            "loss": 0.05406133458018303
        },
        "6": {
            "accuracy": 0.993755,
            "precision": 0.9905971054684115,
            "recall": 0.9568074331394132,
            "f1": 0.9734091247791191,
            "mcc": 0.9700598480801107,
            "missrate": 0.043192566860586784,
            "fallout": 0.0012322054205681774,
            "loss": 0.050382766872644424
        },
        "7": {
            "accuracy": 0.99415,
            "precision": 0.9937850406362727,
            "recall": 0.9570166994517223,
            "f1": 0.9750543686836383,
            "mcc": 0.9719637285132376,
            "missrate": 0.04298330054827774,
            "fallout": 0.0008120063370564486,
            "loss": 0.048006586730480194
        },
        "8": {
            "accuracy": 0.994195,
            "precision": 0.9940879846983134,
            "recall": 0.9571004059766459,
            "f1": 0.9752436189948185,
            "mcc": 0.9721811240267432,
            "missrate": 0.04289959402335412,
            "fallout": 0.0007722577751026364,
            "loss": 0.04396862909197807
        },
        "9": {
            "accuracy": 0.994285,
            "precision": 0.9948233861144945,
            "recall": 0.9571422592391077,
            "f1": 0.9756191207525438,
            "mcc": 0.972616160037576,
            "missrate": 0.04285774076089231,
            "fallout": 0.0006757255532148069,
            "loss": 0.04240183159708977
        },
        "10": {
            "accuracy": 0.994285,
            "precision": 0.9946942680699313,
            "recall": 0.9572678190264932,
            "f1": 0.9756222407063793,
            "mcc": 0.9726160824126554,
            "missrate": 0.04273218097350689,
            "fallout": 0.0006927606511950121,
            "loss": 0.038429144769907,
            "attack_stats": [
                {
                    "attack": "Brute Force",
                    "count": 1306,
                    "correct": 1302,
                    "missed": 4,
                    "percentage": "99.69%"
                },
                {
                    "attack": "DDoS",
                    "count": 14745,
                    "correct": 14722,
                    "missed": 23,
                    "percentage": "99.84%"
                },
                {
                    "attack": "DoS",
                    "count": 5106,
                    "correct": 5078,
                    "missed": 28,
                    "percentage": "99.45%"
                },
                {
                    "attack": "Infilteration",
                    "count": 1231,
                    "correct": 266,
                    "missed": 965,
                    "percentage": "21.61%"
                },
                {
                    "attack": "Bot",
                    "count": 1503,
                    "correct": 1502,
                    "missed": 1,
                    "percentage": "99.93%"
                },
                {
                    "attack": "injection",
                    "count": 2,
                    "correct": 2,
                    "missed": 0,
                    "percentage": "100.00%"
                }
            ]
        }
    },
    "ktkexq_malicious_0": {
        "1": {
            "accuracy": 0.986355,
            "precision": 0.9724528975801411,
            "recall": 0.9116059096806596,
            "f1": 0.941046855760299,
            "mcc": 0.9339635087872042,
            "missrate": 0.0883940903193404,
            "fallout": 0.0035035518179288728,
            "loss": 0.06227315589785576
        },
        "2": {
            "accuracy": 0.988195,
            "precision": 0.9737722232001408,
            "recall": 0.9261289917549073,
            "f1": 0.9493532402342493,
            "mcc": 0.9430567792663678,
            "missrate": 0.07387100824509271,
            "fallout": 0.003384306132067436,
            "loss": 0.04991440102458
        },
        "3": {
            "accuracy": 0.98943,
            "precision": 0.9737654992386339,
            "recall": 0.9367597204202067,
            "f1": 0.9549042194632876,
            "mcc": 0.9491486276981853,
            "missrate": 0.06324027957979325,
            "fallout": 0.0034240546940212486,
            "loss": 0.057494085282087326
        },
        "4": {
            "accuracy": 0.991475,
            "precision": 0.9871344515675771,
            "recall": 0.9409031934039258,
            "f1": 0.9634645466818095,
            "mcc": 0.9589955509769089,
            "missrate": 0.059096806596074164,
            "fallout": 0.0016637612360667095,
            "loss": 0.05693511292338371
        },
        "5": {
            "accuracy": 0.99179,
            "precision": 0.9896140474409189,
            "recall": 0.9411543129786967,
            "f1": 0.9647760425604942,
            "mcc": 0.9605204842825892,
            "missrate": 0.058845687021303314,
            "fallout": 0.0013400943744428103,
            "loss": 0.05406133458018303
        },
        "6": {
            "accuracy": 0.993755,
            "precision": 0.9905971054684115,
            "recall": 0.9568074331394132,
            "f1": 0.9734091247791191,
            "mcc": 0.9700598480801107,
            "missrate": 0.043192566860586784,
            "fallout": 0.0012322054205681774,
            "loss": 0.050382766872644424
        },
        "7": {
            "accuracy": 0.99415,
            "precision": 0.9937850406362727,
            "recall": 0.9570166994517223,
            "f1": 0.9750543686836383,
            "mcc": 0.9719637285132376,
            "missrate": 0.04298330054827774,
            "fallout": 0.0008120063370564486,
            "loss": 0.048006586730480194
        },
        "8": {
            "accuracy": 0.994195,
            "precision": 0.9940879846983134,
            "recall": 0.9571004059766459,
            "f1": 0.9752436189948185,
            "mcc": 0.9721811240267432,
            "missrate": 0.04289959402335412,
            "fallout": 0.0007722577751026364,
            "loss": 0.04396862909197807
        },
        "9": {
            "accuracy": 0.994285,
            "precision": 0.9948233861144945,
            "recall": 0.9571422592391077,
            "f1": 0.9756191207525438,
            "mcc": 0.972616160037576,
            "missrate": 0.04285774076089231,
            "fallout": 0.0006757255532148069,
            "loss": 0.04240183159708977
        },
        "10": {
            "accuracy": 0.994285,
            "precision": 0.9946942680699313,
            "recall": 0.9572678190264932,
            "f1": 0.9756222407063793,
            "mcc": 0.9726160824126554,
            "missrate": 0.04273218097350689,
            "fallout": 0.0006927606511950121,
            "loss": 0.038429144769907,
            "attack_stats": [
                {
                    "attack": "Brute Force",
                    "count": 1306,
                    "correct": 1302,
                    "missed": 4,
                    "percentage": "99.69%"
                },
                {
                    "attack": "DDoS",
                    "count": 14745,
                    "correct": 14722,
                    "missed": 23,
                    "percentage": "99.84%"
                },
                {
                    "attack": "DoS",
                    "count": 5106,
                    "correct": 5078,
                    "missed": 28,
                    "percentage": "99.45%"
                },
                {
                    "attack": "Infilteration",
                    "count": 1231,
                    "correct": 266,
                    "missed": 965,
                    "percentage": "21.61%"
                },
                {
                    "attack": "Bot",
                    "count": 1503,
                    "correct": 1502,
                    "missed": 1,
                    "percentage": "99.93%"
                },
                {
                    "attack": "injection",
                    "count": 2,
                    "correct": 2,
                    "missed": 0,
                    "percentage": "100.00%"
                }
            ]
        }
    },
    "ktkexq_benign_6": {
        "1": {
            "accuracy": 0.986355,
            "precision": 0.9724528975801411,
            "recall": 0.9116059096806596,
            "f1": 0.941046855760299,
            "mcc": 0.9339635087872042,
            "missrate": 0.0883940903193404,
            "fallout": 0.0035035518179288728,
            "loss": 0.06227315589785576
        },
        "2": {
            "accuracy": 0.988195,
            "precision": 0.9737722232001408,
            "recall": 0.9261289917549073,
            "f1": 0.9493532402342493,
            "mcc": 0.9430567792663678,
            "missrate": 0.07387100824509271,
            "fallout": 0.003384306132067436,
            "loss": 0.04991440102458
        },
        "3": {
            "accuracy": 0.98943,
            "precision": 0.9737654992386339,
            "recall": 0.9367597204202067,
            "f1": 0.9549042194632876,
            "mcc": 0.9491486276981853,
            "missrate": 0.06324027957979325,
            "fallout": 0.0034240546940212486,
            "loss": 0.057494085282087326
        },
        "4": {
            "accuracy": 0.991475,
            "precision": 0.9871344515675771,
            "recall": 0.9409031934039258,
            "f1": 0.9634645466818095,
            "mcc": 0.9589955509769089,
            "missrate": 0.059096806596074164,
            "fallout": 0.0016637612360667095,
            "loss": 0.05693511292338371
        },
        "5": {
            "accuracy": 0.99179,
            "precision": 0.9896140474409189,
            "recall": 0.9411543129786967,
            "f1": 0.9647760425604942,
            "mcc": 0.9605204842825892,
            "missrate": 0.058845687021303314,
            "fallout": 0.0013400943744428103,
            "loss": 0.05406133458018303
        },
        "6": {
            "accuracy": 0.993755,
            "precision": 0.9905971054684115,
            "recall": 0.9568074331394132,
            "f1": 0.9734091247791191,
            "mcc": 0.9700598480801107,
            "missrate": 0.043192566860586784,
            "fallout": 0.0012322054205681774,
            "loss": 0.050382766872644424
        },
        "7": {
            "accuracy": 0.99415,
            "precision": 0.9937850406362727,
            "recall": 0.9570166994517223,
            "f1": 0.9750543686836383,
            "mcc": 0.9719637285132376,
            "missrate": 0.04298330054827774,
            "fallout": 0.0008120063370564486,
            "loss": 0.048006586730480194
        },
        "8": {
            "accuracy": 0.994195,
            "precision": 0.9940879846983134,
            "recall": 0.9571004059766459,
            "f1": 0.9752436189948185,
            "mcc": 0.9721811240267432,
            "missrate": 0.04289959402335412,
            "fallout": 0.0007722577751026364,
            "loss": 0.04396862909197807
        },
        "9": {
            "accuracy": 0.994285,
            "precision": 0.9948233861144945,
            "recall": 0.9571422592391077,
            "f1": 0.9756191207525438,
            "mcc": 0.972616160037576,
            "missrate": 0.04285774076089231,
            "fallout": 0.0006757255532148069,
            "loss": 0.04240183159708977
        },
        "10": {
            "accuracy": 0.994285,
            "precision": 0.9946942680699313,
            "recall": 0.9572678190264932,
            "f1": 0.9756222407063793,
            "mcc": 0.9726160824126554,
            "missrate": 0.04273218097350689,
            "fallout": 0.0006927606511950121,
            "loss": 0.038429144769907,
            "attack_stats": [
                {
                    "attack": "Brute Force",
                    "count": 1306,
                    "correct": 1302,
                    "missed": 4,
                    "percentage": "99.69%"
                },
                {
                    "attack": "DDoS",
                    "count": 14745,
                    "correct": 14722,
                    "missed": 23,
                    "percentage": "99.84%"
                },
                {
                    "attack": "DoS",
                    "count": 5106,
                    "correct": 5078,
                    "missed": 28,
                    "percentage": "99.45%"
                },
                {
                    "attack": "Infilteration",
                    "count": 1231,
                    "correct": 266,
                    "missed": 965,
                    "percentage": "21.61%"
                },
                {
                    "attack": "Bot",
                    "count": 1503,
                    "correct": 1502,
                    "missed": 1,
                    "percentage": "99.93%"
                },
                {
                    "attack": "injection",
                    "count": 2,
                    "correct": 2,
                    "missed": 0,
                    "percentage": "100.00%"
                }
            ]
        }
    },
    "ktkexq_benign_2": {
        "1": {
            "accuracy": 0.986355,
            "precision": 0.9724528975801411,
            "recall": 0.9116059096806596,
            "f1": 0.941046855760299,
            "mcc": 0.9339635087872042,
            "missrate": 0.0883940903193404,
            "fallout": 0.0035035518179288728,
            "loss": 0.06227315589785576
        },
        "2": {
            "accuracy": 0.988195,
            "precision": 0.9737722232001408,
            "recall": 0.9261289917549073,
            "f1": 0.9493532402342493,
            "mcc": 0.9430567792663678,
            "missrate": 0.07387100824509271,
            "fallout": 0.003384306132067436,
            "loss": 0.04991440102458
        },
        "3": {
            "accuracy": 0.98943,
            "precision": 0.9737654992386339,
            "recall": 0.9367597204202067,
            "f1": 0.9549042194632876,
            "mcc": 0.9491486276981853,
            "missrate": 0.06324027957979325,
            "fallout": 0.0034240546940212486,
            "loss": 0.057494085282087326
        },
        "4": {
            "accuracy": 0.991475,
            "precision": 0.9871344515675771,
            "recall": 0.9409031934039258,
            "f1": 0.9634645466818095,
            "mcc": 0.9589955509769089,
            "missrate": 0.059096806596074164,
            "fallout": 0.0016637612360667095,
            "loss": 0.05693511292338371
        },
        "5": {
            "accuracy": 0.99179,
            "precision": 0.9896140474409189,
            "recall": 0.9411543129786967,
            "f1": 0.9647760425604942,
            "mcc": 0.9605204842825892,
            "missrate": 0.058845687021303314,
            "fallout": 0.0013400943744428103,
            "loss": 0.05406133458018303
        },
        "6": {
            "accuracy": 0.993755,
            "precision": 0.9905971054684115,
            "recall": 0.9568074331394132,
            "f1": 0.9734091247791191,
            "mcc": 0.9700598480801107,
            "missrate": 0.043192566860586784,
            "fallout": 0.0012322054205681774,
            "loss": 0.050382766872644424
        },
        "7": {
            "accuracy": 0.99415,
            "precision": 0.9937850406362727,
            "recall": 0.9570166994517223,
            "f1": 0.9750543686836383,
            "mcc": 0.9719637285132376,
            "missrate": 0.04298330054827774,
            "fallout": 0.0008120063370564486,
            "loss": 0.048006586730480194
        },
        "8": {
            "accuracy": 0.994195,
            "precision": 0.9940879846983134,
            "recall": 0.9571004059766459,
            "f1": 0.9752436189948185,
            "mcc": 0.9721811240267432,
            "missrate": 0.04289959402335412,
            "fallout": 0.0007722577751026364,
            "loss": 0.04396862909197807
        },
        "9": {
            "accuracy": 0.994285,
            "precision": 0.9948233861144945,
            "recall": 0.9571422592391077,
            "f1": 0.9756191207525438,
            "mcc": 0.972616160037576,
            "missrate": 0.04285774076089231,
            "fallout": 0.0006757255532148069,
            "loss": 0.04240183159708977
        },
        "10": {
            "accuracy": 0.994285,
            "precision": 0.9946942680699313,
            "recall": 0.9572678190264932,
            "f1": 0.9756222407063793,
            "mcc": 0.9726160824126554,
            "missrate": 0.04273218097350689,
            "fallout": 0.0006927606511950121,
            "loss": 0.038429144769907,
            "attack_stats": [
                {
                    "attack": "Brute Force",
                    "count": 1306,
                    "correct": 1302,
                    "missed": 4,
                    "percentage": "99.69%"
                },
                {
                    "attack": "DDoS",
                    "count": 14745,
                    "correct": 14722,
                    "missed": 23,
                    "percentage": "99.84%"
                },
                {
                    "attack": "DoS",
                    "count": 5106,
                    "correct": 5078,
                    "missed": 28,
                    "percentage": "99.45%"
                },
                {
                    "attack": "Infilteration",
                    "count": 1231,
                    "correct": 266,
                    "missed": 965,
                    "percentage": "21.61%"
                },
                {
                    "attack": "Bot",
                    "count": 1503,
                    "correct": 1502,
                    "missed": 1,
                    "percentage": "99.93%"
                },
                {
                    "attack": "injection",
                    "count": 2,
                    "correct": 2,
                    "missed": 0,
                    "percentage": "100.00%"
                }
            ]
        }
    }
}