{
    "qture6": {
        "qture6_benign_0": {
            "train": {
                "Benign": 70465,
                "Brute Force": 516
            },
            "test": {
                "Benign": 175977,
                "DDoS": 14726,
                "DoS": 5164,
                "Bot": 1577,
                "Brute Force": 1358,
                "Infilteration": 1197,
                "injection": 1
            }
        },
        "qture6_benign_1": {
            "train": {
                "Benign": 70465,
                "Infilteration": 496
            },
            "test": {
                "Benign": 175977,
                "DDoS": 14726,
                "DoS": 5164,
                "Bot": 1577,
                "Brute Force": 1358,
                "Infilteration": 1197,
                "injection": 1
            }
        },
        "qture6_benign_2": {
            "train": {
                "Benign": 70465,
                "Infilteration": 496
            },
            "test": {
                "Benign": 175977,
                "DDoS": 14726,
                "DoS": 5164,
                "Bot": 1577,
                "Brute Force": 1358,
                "Infilteration": 1197,
                "injection": 1
            }
        },
        "qture6_benign_3": {
            "train": {
                "Benign": 70465,
                "DoS": 2042
            },
            "test": {
                "Benign": 175977,
                "DDoS": 14726,
                "DoS": 5164,
                "Bot": 1577,
                "Brute Force": 1358,
                "Infilteration": 1197,
                "injection": 1
            }
        },
        "qture6_benign_4": {
            "train": {
                "Benign": 70465,
                "Bot": 600
            },
            "test": {
                "Benign": 175977,
                "DDoS": 14726,
                "DoS": 5164,
                "Bot": 1577,
                "Brute Force": 1358,
                "Infilteration": 1197,
                "injection": 1
            }
        },
        "qture6_benign_5": {
            "train": {
                "Benign": 70465,
                "DDoS": 5879
            },
            "test": {
                "Benign": 175977,
                "DDoS": 14726,
                "DoS": 5164,
                "Bot": 1577,
                "Brute Force": 1358,
                "Infilteration": 1197,
                "injection": 1
            }
        },
        "qture6_benign_6": {
            "train": {
                "Benign": 70464,
                "Brute Force": 516
            },
            "test": {
                "Benign": 175977,
                "DDoS": 14726,
                "DoS": 5164,
                "Bot": 1577,
                "Brute Force": 1358,
                "Infilteration": 1197,
                "injection": 1
            }
        },
        "qture6_benign_7": {
            "train": {
                "Benign": 70464,
                "Bot": 600
            },
            "test": {
                "Benign": 175977,
                "DDoS": 14726,
                "DoS": 5164,
                "Bot": 1577,
                "Brute Force": 1358,
                "Infilteration": 1197,
                "injection": 1
            }
        },
        "qture6_benign_8": {
            "train": {
                "Benign": 70464,
                "Bot": 600
            },
            "test": {
                "Benign": 175977,
                "DDoS": 14726,
                "DoS": 5164,
                "Bot": 1577,
                "Brute Force": 1358,
                "Infilteration": 1197,
                "injection": 1
            }
        },
        "qture6_malicious_0": {
            "train": {
                "Benign": 70464,
                "Brute Force": 521
            },
            "test": {
                "Benign": 175977,
                "DDoS": 14726,
                "DoS": 5164,
                "Bot": 1577,
                "Brute Force": 1358,
                "Infilteration": 1197,
                "injection": 1
            }
        }
    }
}